soundbridgefx/__init__.py
soundbridgefx/__main__.py
soundbridgefx/config.py
soundbridgefx/ffmpeg.py
soundbridgefx/ledfx.py
soundbridgefx/parser.py
soundbridgefx/raspotify.py
soundbridgefx/sonosspeaker.py
soundbridgefx/sonosspeakers.py
soundbridgefx/speaker_api.py
soundbridgefx/speakers.py
soundbridgefx/stream_api.py
soundbridgefx/web/client/_app/immutable/assets/_layout.b09eff48.css
soundbridgefx/web/client/_app/immutable/assets/_page.ad402662.css
soundbridgefx/web/client/_app/immutable/chunks/0.78150b7d.js
soundbridgefx/web/client/_app/immutable/chunks/0.873917be.js
soundbridgefx/web/client/_app/immutable/chunks/1.36106bc2.js
soundbridgefx/web/client/_app/immutable/chunks/2.2348a9e9.js
soundbridgefx/web/client/_app/immutable/chunks/2.fa134829.js
soundbridgefx/web/client/_app/immutable/chunks/3.9133445b.js
soundbridgefx/web/client/_app/immutable/chunks/4.93330022.js
soundbridgefx/web/client/_app/immutable/chunks/5.29f12f72.js
soundbridgefx/web/client/_app/immutable/chunks/5.506341a8.js
soundbridgefx/web/client/_app/immutable/chunks/5.74a9f993.js
soundbridgefx/web/client/_app/immutable/chunks/Ripple.6b4d2b6a.js
soundbridgefx/web/client/_app/immutable/chunks/_layout.da46b06b.js
soundbridgefx/web/client/_app/immutable/chunks/index.72b3cb36.js
soundbridgefx/web/client/_app/immutable/chunks/index.a6ab0d54.js
soundbridgefx/web/client/_app/immutable/entry/_error.svelte.6b5b3453.js
soundbridgefx/web/client/_app/immutable/entry/_layout.js.984db11e.js
soundbridgefx/web/client/_app/immutable/entry/_layout.svelte.53f5fc93.js
soundbridgefx/web/client/_app/immutable/entry/_layout.svelte.ff54b69b.js
soundbridgefx/web/client/_app/immutable/entry/_page.svelte.53000b6a.js
soundbridgefx/web/client/_app/immutable/entry/_page.svelte.acd01710.js
soundbridgefx/web/client/_app/immutable/entry/app.891c6909.js
soundbridgefx/web/client/_app/immutable/entry/app.a46e7f13.js
soundbridgefx/web/client/_app/immutable/entry/app.d3c452e9.js
soundbridgefx-0.2.1b0.dist-info/LICENSE
soundbridgefx-0.2.1b0.dist-info/METADATA
soundbridgefx-0.2.1b0.dist-info/WHEEL
soundbridgefx-0.2.1b0.dist-info/entry_points.txt
soundbridgefx-0.2.1b0.dist-info/RECORD
